{"appleSKU":"","appleTeamID":"","enableCodelessAutoInitialization":true,"enableUnityGamingServicesAutoInitialization":false,"products":[{"id":"com.melisalpkaya.blueShip","type":1,"storeIDs":[],"defaultDescription":{"googleLocale":4,"title":"Blue Ship","description":""},"screenshotPath":"","applePriceTier":3,"googlePrice":{"data":[10,0,0,0],"num":10.0},"pricingTemplateID":"","descriptions":[],"udpPrice":{"data":[0,0,0,0],"num":0.0},"payouts":[]},{"id":"com.melisalpkaya.redShip","type":1,"storeIDs":[],"defaultDescription":{"googleLocale":4,"title":"Red Ship","description":""},"screenshotPath":"","applePriceTier":4,"googlePrice":{"data":[20,0,0,0],"num":20.0},"pricingTemplateID":"","descriptions":[],"udpPrice":{"data":[0,0,0,0],"num":0.0},"payouts":[]},{"id":"com.melisalpkaya.greenShip","type":0,"storeIDs":[],"defaultDescription":{"googleLocale":4,"title":"","description":""},"screenshotPath":"","applePriceTier":5,"googlePrice":{"data":[30,0,0,0],"num":30.0},"pricingTemplateID":"","descriptions":[],"udpPrice":{"data":[0,0,0,0],"num":0.0},"payouts":[]},{"id":"","type":0,"storeIDs":[],"defaultDescription":{"googleLocale":4,"title":"","description":""},"screenshotPath":"","applePriceTier":0,"googlePrice":{"data":[0,0,0,0],"num":0.0},"pricingTemplateID":"","descriptions":[],"udpPrice":{"data":[0,0,0,0],"num":0.0},"payouts":[]}]}